[
	{
		"datetime": "2025-09-26T20:15",
		"venue": "Aylesbury High School, Walton Road, Aylesbury, HP21 7SX",
		"mapLink": "https://maps.app.goo.gl/BaT3DF9RnMhjn4pn9",
		"homeTeam": "Aylesbury Dux Masters",
		"awayTeam": "Ravens (forfeit)",
		"homeScore": "",
		"awayScore": "",
		"squad": [],
		"officials": []
	},
	{
		"datetime": "2025-11-03T20:15",
		"venue": "Sports Hall Building 19, Cranfield University, Lanchester Road, Cranfield, Mk43 0AL",
		"mapLink": "https://maps.app.goo.gl/5aGzMgTyKsbqt4yL6",
		"homeTeam": "Cranfield",
		"awayTeam": "Ravens",
		"homeScore": "51",
		"awayScore": "27",
		"scoresheet": 1,
		"squad": [
			{
				"kit": "0",
				"givenName": "Keith",
				"familyName": "Bragg",
				"available": 1
			},
			{
				"kit": "4",
				"givenName": "David",
				"familyName": "Shore",
				"available": 1
			},
			{
				"kit": "5",
				"givenName": "Dominic",
				"familyName": "Garcia",
				"available": 0
			},
			{
				"kit": "6",
				"givenName": "Richard",
				"familyName": "Herbert",
				"available": 0
			},
			{
				"kit": "7",
				"givenName": "Otto",
				"familyName": "Opiyo",
				"available": 1
			},
			{
				"kit": "11",
				"givenName": "Cameron",
				"familyName": "Walters",
				"available": 0
			},
			{
				"kit": "14",
				"givenName": "Simon",
				"familyName": "Jackson-Turner",
				"available": 0
			},
			{
				"kit": "17",
				"givenName": "Dan",
				"familyName": "Large",
				"available": 1
			},
			{
				"kit": "22",
				"givenName": "Damir",
				"familyName": "Davis",
				"available": 0
			},
			{
				"kit": "24",
				"givenName": "Gaetano",
				"familyName": "Lo Nigro",
				"available": 1
			},
			{
				"kit": "28",
				"givenName": "Greg",
				"familyName": "Seymour",
				"available": 0
			},
			{
				"kit": "33",
				"givenName": "Neil",
				"familyName": "McCutcheon",
				"available": 1
			},
			{
				"kit": "49",
				"givenName": "Dan",
				"familyName": "Bernard",
				"available": 0
			},
			{
				"kit": "55",
				"givenName": "Lester",
				"familyName": "Confessor",
				"available": 1
			}
		],
		"officials": []
	},
	{
		"datetime": "2025-10-10T20:15",
		"venue": "Aylesbury High School, Walton Road, Aylesbury, HP21 7SX",
		"mapLink": "https://maps.app.goo.gl/BaT3DF9RnMhjn4pn9",
		"homeTeam": "Aylesbury Dux Masters",
		"awayTeam": "Ravens (Cup)",
		"homeScore": "66",
		"awayScore": "34",
		"scoresheet": 1,
		"stats": 1,
		"videoURL": "https://youtu.be/_ij15_BCP7M",
		"squad": [],
		"officials": []
	},
	{
		"datetime": "2025-10-13T20:15",
		"venue": "Onslow St Audrey's School, Old Rectory Drive, Hatfield, AL10 8AB",
		"mapLink": "https://maps.app.goo.gl/GwVjSFaKvrV3f3THA",
		"homeTeam": "Ravens",
		"awayTeam": "Herts Heat",
		"homeScore": "16",
		"awayScore": "73",
		"scoresheet": 1,
		"stats": 1,
		"videoURL": "https://app.veo.co/matches/20251013-recording-bafa-a3c7b9f2/",
		"squad": [],
		"officials": []
	},
	{
		"datetime": "2025-10-28T20:15",
		"venue": "Birchwood Leisure Centre, Hatfield, AL10 0AN",
		"mapLink": "https://maps.app.goo.gl/6crmfBtPLiB6fT7B7",
		"homeTeam": "Birchwood Braves",
		"awayTeam": "Ravens (forfeit)",
		"homeScore": "",
		"awayScore": "",
		"squad": [],
		"officials": []
	},
	{
		"datetime": "2025-10-23T20:15",
		"venue": "Haberdashers' Boys' School, Butterfly Ln, Elstree, Radlett, Borehamwood WD6 3AF",
		"mapLink": "https://maps.app.goo.gl/gwSw6JuR3AzKhUrv8",
		"homeTeam": "West Herts Warriors",
		"awayTeam": "Ravens",
		"homeScore": "65",
		"awayScore": "28",
		"scoresheet": 1,
		"stats": 1,
		"squad": [],
		"officials": []
	},
	{
		"datetime": "2025-11-07T20:15",
		"venue": "Longdean Sports Centre, Hill Common, Hemel Hempstead, HP3 8JH",
		"mapLink": "https://maps.app.goo.gl/uv9v4RL8yayjmwA58",
		"homeTeam": "Watford Hongkongers",
		"awayTeam": "Ravens",
		"homeScore": "59",
		"awayScore": "52",
		"scoresheet": 1,
		"squad": [
			{
				"kit": "11",
				"givenName": "Cameron",
				"familyName": "Walters",
				"available": 0
			},
			{
				"kit": "22",
				"givenName": "Damir",
				"familyName": "Davis",
				"available": 0
			},
			{
				"kit": "49",
				"givenName": "Dan",
				"familyName": "Bernard",
				"available": 1
			},
			{
				"kit": "17",
				"givenName": "Dan",
				"familyName": "Large",
				"available": 1
			},
			{
				"kit": "4",
				"givenName": "David",
				"familyName": "Shore",
				"available": 1
			},
			{
				"kit": "5",
				"givenName": "Dominic",
				"familyName": "Garcia",
				"available": 1
			},
			{
				"kit": "24",
				"givenName": "Gaetano",
				"familyName": "Lo Nigro",
				"available": 1
			},
			{
				"kit": "28",
				"givenName": "Greg",
				"familyName": "Seymour",
				"available": 0
			},
			{
				"kit": "0",
				"givenName": "Keith",
				"familyName": "Bragg",
				"available": 0
			},
			{
				"kit": "55",
				"givenName": "Lester",
				"familyName": "Confessor",
				"available": 1
			},
			{
				"kit": "33",
				"givenName": "Neil",
				"familyName": "McCutcheon",
				"available": 0
			},
			{
				"kit": "7",
				"givenName": "Otto",
				"familyName": "Opiyo",
				"available": 1
			},
			{
				"kit": "6",
				"givenName": "Richard",
				"familyName": "Herbert",
				"available": 0
			},
			{
				"kit": "14",
				"givenName": "Simon",
				"familyName": "Jackson-Turner",
				"available": 1
			}
		],
		"officials": []
	},
	{
		"datetime": "2025-11-09T18:15",
		"venue": "Aylesbury High School, Walton Road, Aylesbury, HP21 7SX",
		"mapLink": "https://maps.app.goo.gl/BaT3DF9RnMhjn4pn9",
		"homeTeam": "Aylesbury Dux Rebels",
		"awayTeam": "Ravens",
		"homeScore": "88",
		"awayScore": "46",
		"stats": 1,
		"videoURL": "https://youtu.be/vFUTiESl6wY?si=9CuBVT207qZGOZ1S",
		"squad": [
			{
				"kit": "11",
				"givenName": "Cameron",
				"familyName": "Walters",
				"available": 0
			},
			{
				"kit": "22",
				"givenName": "Damir",
				"familyName": "Davis",
				"available": 1
			},
			{
				"kit": "49",
				"givenName": "Dan",
				"familyName": "Bernard",
				"available": 1
			},
			{
				"kit": "17",
				"givenName": "Dan",
				"familyName": "Large",
				"available": 1
			},
			{
				"kit": "4",
				"givenName": "David",
				"familyName": "Shore",
				"available": 1
			},
			{
				"kit": "5",
				"givenName": "Dominic",
				"familyName": "Garcia",
				"available": 1
			},
			{
				"kit": "24",
				"givenName": "Gaetano",
				"familyName": "Lo Nigro",
				"available": 1
			},
			{
				"kit": "28",
				"givenName": "Greg",
				"familyName": "Seymour",
				"available": 0
			},
			{
				"kit": "0",
				"givenName": "Keith",
				"familyName": "Bragg",
				"available": 0
			},
			{
				"kit": "55",
				"givenName": "Lester",
				"familyName": "Confessor",
				"available": 1
			},
			{
				"kit": "33",
				"givenName": "Neil",
				"familyName": "McCutcheon",
				"available": 0
			},
			{
				"kit": "7",
				"givenName": "Otto",
				"familyName": "Opiyo",
				"available": 0
			},
			{
				"kit": "6",
				"givenName": "Richard",
				"familyName": "Herbert",
				"available": 0
			},
			{
				"kit": "14",
				"givenName": "Simon",
				"familyName": "Jackson-Turner",
				"available": 1
			}
		]
		,
		"officials": []
	},
	{
		"datetime": "2025-11-17T20:15",
		"venue": "Onslow St Audrey's School, Old Rectory Drive, Hatfield, AL10 8AB",
		"mapLink": "https://maps.app.goo.gl/GwVjSFaKvrV3f3THA",
		"homeTeam": "Ravens (WHITE)",
		"awayTeam": "North Herts Knights 2",
		"homeScore": "31",
		"awayScore": "62",
		"scoresheet": 1,
		"stats": 1,
		"squad": [
			{
				"kit": "11",
				"givenName": "Cameron",
				"familyName": "Walters",
				"available": 0
			},
			{
				"kit": "22",
				"givenName": "Damir",
				"familyName": "Davis",
				"available": 0
			},
			{
				"kit": "49",
				"givenName": "Dan",
				"familyName": "Bernard",
				"available": 1
			},
			{
				"kit": "17",
				"givenName": "Dan",
				"familyName": "Large",
				"available": 0
			},
			{
				"kit": "4",
				"givenName": "David",
				"familyName": "Shore",
				"available": 1
			},
			{
				"kit": "5",
				"givenName": "Dominic",
				"familyName": "Garcia",
				"available": 0
			},
			{
				"kit": "24",
				"givenName": "Gaetano",
				"familyName": "Lo Nigro",
				"available": 1
			},
			{
				"kit": "28",
				"givenName": "Greg",
				"familyName": "Seymour",
				"available": 0
			},
			{
				"kit": "0",
				"givenName": "Keith",
				"familyName": "Bragg",
				"available": 0
			},
			{
				"kit": "55",
				"givenName": "Lester",
				"familyName": "Confessor",
				"available": 1
			},
			{
				"kit": "33",
				"givenName": "Neil",
				"familyName": "McCutcheon",
				"available": 0
			},
			{
				"kit": "7",
				"givenName": "Otto",
				"familyName": "Opiyo",
				"available": 1
			},
			{
				"kit": "6",
				"givenName": "Richard",
				"familyName": "Herbert",
				"available": 0
			},
			{
				"kit": "14",
				"givenName": "Simon",
				"familyName": "Jackson-Turner",
				"available": 1
			}
		],
		"officials": []
	},
	{
		"datetime": "2025-11-24T20:15",
		"venue": "Onslow St Audrey's School, Old Rectory Drive, Hatfield, AL10 8AB",
		"mapLink": "https://maps.app.goo.gl/GwVjSFaKvrV3f3THA",
		"homeTeam": "Ravens (WHITE)",
		"awayTeam": "Birchwood Braves",
		"homeScore": "20",
		"awayScore": "57",
		"scoresheet": 1,
		"stats": 1,
		"squad": [
			{
				"kit": "11",
				"givenName": "Cameron",
				"familyName": "Walters",
				"available": 0
			},
			{
				"kit": "22",
				"givenName": "Damir",
				"familyName": "Davis",
				"available": 0
			},
			{
				"kit": "49",
				"givenName": "Dan",
				"familyName": "Bernard",
				"available": 1
			},
			{
				"kit": "17",
				"givenName": "Dan",
				"familyName": "Large",
				"available": 1
			},
			{
				"kit": "4",
				"givenName": "David",
				"familyName": "Shore",
				"available": 1
			},
			{
				"kit": "5",
				"givenName": "Dominic",
				"familyName": "Garcia",
				"available": 1
			},
			{
				"kit": "24",
				"givenName": "Gaetano",
				"familyName": "Lo Nigro",
				"available": 1
			},
			{
				"kit": "28",
				"givenName": "Greg",
				"familyName": "Seymour",
				"available": 0
			},
			{
				"kit": "0",
				"givenName": "Keith",
				"familyName": "Bragg",
				"available": 1
			},
			{
				"kit": "55",
				"givenName": "Lester",
				"familyName": "Confessor",
				"available": 1
			},
			{
				"kit": "33",
				"givenName": "Neil",
				"familyName": "McCutcheon",
				"available": 0
			},
			{
				"kit": "7",
				"givenName": "Otto",
				"familyName": "Opiyo",
				"available": 1
			},
			{
				"kit": "6",
				"givenName": "Richard",
				"familyName": "Herbert",
				"available": 0
			},
			{
				"kit": "14",
				"givenName": "Simon",
				"familyName": "Jackson-Turner",
				"available": 0
			}
		],
		"officials": []
	},
	{
		"datetime": "2025-12-08T20:15",
		"venue": "Onslow St Audrey's School, Old Rectory Drive, Hatfield, AL10 8AB",
		"mapLink": "https://maps.app.goo.gl/GwVjSFaKvrV3f3THA",
		"homeTeam": "Ravens (WHITE)",
		"awayTeam": "Cranfield (BLUE)",
		"homeScore": "25",
		"awayScore": "122",
		"scoresheet": 1,
		"stats": 1,
		"squad": [
			{
				"kit": "11",
				"givenName": "Cameron",
				"familyName": "Walters",
				"available": 0
			},
			{
				"kit": "22",
				"givenName": "Damir",
				"familyName": "Davis",
				"available": 0
			},
			{
				"kit": "49",
				"givenName": "Dan",
				"familyName": "Bernard",
				"available": 1
			},
			{
				"kit": "17",
				"givenName": "Dan",
				"familyName": "Large",
				"available": 1
			},
			{
				"kit": "4",
				"givenName": "David",
				"familyName": "Shore",
				"available": 1
			},
			{
				"kit": "5",
				"givenName": "Dominic",
				"familyName": "Garcia",
				"available": 1
			},
			{
				"kit": "24",
				"givenName": "Gaetano",
				"familyName": "Lo Nigro",
				"available": 1
			},
			{
				"kit": "28",
				"givenName": "Greg",
				"familyName": "Seymour",
				"available": 0
			},
			{
				"kit": "0",
				"givenName": "Keith",
				"familyName": "Bragg",
				"available": 1
			},
			{
				"kit": "55",
				"givenName": "Lester",
				"familyName": "Confessor",
				"available": 0
			},
			{
				"kit": "33",
				"givenName": "Neil",
				"familyName": "McCutcheon",
				"available": 1
			},
			{
				"kit": "7",
				"givenName": "Otto",
				"familyName": "Opiyo",
				"available": 0
			},
			{
				"kit": "6",
				"givenName": "Richard",
				"familyName": "Herbert",
				"available": 1
			},
			{
				"kit": "14",
				"givenName": "Simon",
				"familyName": "Jackson-Turner",
				"available": 1
			}
		],
		"officials": []
	},
	{
		"datetime": "2025-12-16T20:15",
		"venue": "Chancellor's Secondary School, Pine Grove, Brookmans Park, Hatfield AL9 7BN",
		"mapLink": "https://maps.app.goo.gl/gsmAHD5P9W1Vwsm26",
		"homeTeam": "Ravens (BLACK)",
		"awayTeam": "Watford Hongkongers (WHITE)",
		"homeScore": "36",
		"awayScore": "72",
		"scoresheet": 1,
		"stats": 1,
		"squad": [
			{
				"kit": "11",
				"givenName": "Cameron",
				"familyName": "Walters",
				"available": 0
			},
			{
				"kit": "22",
				"givenName": "Damir",
				"familyName": "Davis",
				"available": 1
			},
			{
				"kit": "49",
				"givenName": "Dan",
				"familyName": "Bernard",
				"available": 1
			},
			{
				"kit": "17",
				"givenName": "Dan",
				"familyName": "Large",
				"available": 1
			},
			{
				"kit": "4",
				"givenName": "David",
				"familyName": "Shore",
				"available": 1
			},
			{
				"kit": "5",
				"givenName": "Dominic",
				"familyName": "Garcia",
				"available": 0
			},
			{
				"kit": "24",
				"givenName": "Gaetano",
				"familyName": "Lo Nigro",
				"available": 1
			},
			{
				"kit": "28",
				"givenName": "Greg",
				"familyName": "Seymour",
				"available": 0
			},
			{
				"kit": "0",
				"givenName": "Keith",
				"familyName": "Bragg",
				"available": 1
			},
			{
				"kit": "55",
				"givenName": "Lester",
				"familyName": "Confessor",
				"available": 1
			},
			{
				"kit": "33",
				"givenName": "Neil",
				"familyName": "McCutcheon",
				"available": 0
			},
			{
				"kit": "7",
				"givenName": "Otto",
				"familyName": "Opiyo",
				"available": 1
			},
			{
				"kit": "6",
				"givenName": "Richard",
				"familyName": "Herbert",
				"available": 1
			},
			{
				"kit": "14",
				"givenName": "Simon",
				"familyName": "Jackson-Turner",
				"available": 1
			}
		],
		"officials": []
	},
	{
		"datetime": "2025-12-19T20:15",
		"venue": "Houston Secondary School, Parkside Drive, Houghton Regis, Dunstable, LU5 5PX",
		"mapLink": "https://maps.app.goo.gl/XG4DEzEd3EtDsxPU7",
		"homeTeam": "Hemel Wolves 2 (WHITE)",
		"awayTeam": "Ravens (BLACK)",
		"homeScore": "70",
		"awayScore": "38",
		"scoresheet": 1,
		"stats": 1,
		"videoURL": "https://www.youtube.com/live/-G96gGVFw5g?si=iRPHjGbTti67OKVR",
		"squad": [
		{
			"kit": "11",
			"givenName": "Cameron",
			"familyName": "Walters",
			"available": 0
		},
		{
			"kit": "22",
			"givenName": "Damir",
			"familyName": "Davis",
			"available": 1
		},
		{
			"kit": "49",
			"givenName": "Dan",
			"familyName": "Bernard",
			"available": 1
		},
		{
			"kit": "17",
			"givenName": "Dan",
			"familyName": "Large",
			"available": 1
		},
		{
			"kit": "4",
			"givenName": "David",
			"familyName": "Shore",
			"available": 1
		},
		{
			"kit": "5",
			"givenName": "Dominic",
			"familyName": "Garcia",
			"available": 0
		},
		{
			"kit": "24",
			"givenName": "Gaetano",
			"familyName": "Lo Nigro",
			"available": 1
		},
		{
			"kit": "28",
			"givenName": "Greg",
			"familyName": "Seymour",
			"available": 0
		},
		{
			"kit": "0",
			"givenName": "Keith",
			"familyName": "Bragg",
			"available": 0
		},
		{
			"kit": "55",
			"givenName": "Lester",
			"familyName": "Confessor",
			"available": 0
		},
		{
			"kit": "33",
			"givenName": "Neil",
			"familyName": "McCutcheon",
			"available": 1
		},
		{
			"kit": "7",
			"givenName": "Otto",
			"familyName": "Opiyo",
			"available": 0
		},
		{
			"kit": "6",
			"givenName": "Richard",
			"familyName": "Herbert",
			"available": 1
		},
		{
			"kit": "14",
			"givenName": "Simon",
			"familyName": "Jackson-Turner",
			"available": 0
		}
	],
		"officials": []
	},
	{
		"datetime": "2025-12-01T20:15",
		"venue": "Onslow St Audrey's School, Old Rectory Drive, Hatfield, AL10 8AB",
		"mapLink": "https://maps.app.goo.gl/GwVjSFaKvrV3f3THA",
		"homeTeam": "Ravens (BLACK)",
		"awayTeam": "Aylesbury Dux Masters (WHITE)",
		"homeScore": "17",
		"awayScore": "63",
		"scoresheet": 1,
		"stats": 1,
		"squad": [
			{
				"kit": "11",
				"givenName": "Cameron",
				"familyName": "Walters",
				"available": 0
			},
			{
				"kit": "22",
				"givenName": "Damir",
				"familyName": "Davis",
				"available": 0
			},
			{
				"kit": "49",
				"givenName": "Dan",
				"familyName": "Bernard",
				"available": 1
			},
			{
				"kit": "17",
				"givenName": "Dan",
				"familyName": "Large",
				"available": 1
			},
			{
				"kit": "4",
				"givenName": "David",
				"familyName": "Shore",
				"available": 1
			},
			{
				"kit": "5",
				"givenName": "Dominic",
				"familyName": "Garcia",
				"available": 1
			},
			{
				"kit": "24",
				"givenName": "Gaetano",
				"familyName": "Lo Nigro",
				"available": 1
			},
			{
				"kit": "28",
				"givenName": "Greg",
				"familyName": "Seymour",
				"available": 0
			},
			{
				"kit": "0",
				"givenName": "Keith",
				"familyName": "Bragg",
				"available": 1
			},
			{
				"kit": "55",
				"givenName": "Lester",
				"familyName": "Confessor",
				"available": 1
			},
			{
				"kit": "33",
				"givenName": "Neil",
				"familyName": "McCutcheon",
				"available": 0
			},
			{
				"kit": "7",
				"givenName": "Otto",
				"familyName": "Opiyo",
				"available": 1
			},
			{
				"kit": "6",
				"givenName": "Richard",
				"familyName": "Herbert",
				"available": 0
			},
			{
				"kit": "14",
				"givenName": "Simon",
				"familyName": "Jackson-Turner",
				"available": 0
			}
		],
		"officials": []
	},
	{
		"datetime": "2026-02-09T20:15",
		"venue": "Onslow St Audrey's School, Old Rectory Drive, Hatfield, AL10 8AB",
		"mapLink": "https://maps.app.goo.gl/GwVjSFaKvrV3f3THA",
		"homeTeam": "Ravens (WHITE)",
		"awayTeam": "West Herts Warriors",
		"homeScore": "41",
		"awayScore": "72",
		"scoresheet": 0,
		"stats": 1,
		"squad": [
			{
				"kit": "11",
				"givenName": "Cameron",
				"familyName": "Walters",
				"available": 0
			},
			{
				"kit": "22",
				"givenName": "Damir",
				"familyName": "Davis",
				"available": 0
			},
			{
				"kit": "49",
				"givenName": "Dan",
				"familyName": "Bernard",
				"available": 1
			},
			{
				"kit": "17",
				"givenName": "Dan",
				"familyName": "Large",
				"available": 1
			},
			{
				"kit": "4",
				"givenName": "David",
				"familyName": "Shore",
				"available": 1
			},
			{
				"kit": "5",
				"givenName": "Dominic",
				"familyName": "Garcia",
				"available": 0
			},
			{
				"kit": "24",
				"givenName": "Gaetano",
				"familyName": "Lo Nigro",
				"available": 1
			},
			{
				"kit": "28",
				"givenName": "Greg",
				"familyName": "Seymour",
				"available": 0
			},
			{
				"kit": "0",
				"givenName": "Keith",
				"familyName": "Bragg",
				"available": 1
			},
			{
				"kit": "55",
				"givenName": "Lester",
				"familyName": "Confessor",
				"available": 0
			},
			{
				"kit": "33",
				"givenName": "Neil",
				"familyName": "McCutcheon",
				"available": 1
			},
			{
				"kit": "7",
				"givenName": "Otto",
				"familyName": "Opiyo",
				"available": 1
			},
			{
				"kit": "6",
				"givenName": "Richard",
				"familyName": "Herbert",
				"available": 1
			},
			{
				"kit": "14",
				"givenName": "Simon",
				"familyName": "Jackson-Turner",
				"available": 0
			}
		],
		"officials": []
	},
	{
		"datetime": "2026-01-14T19:50",
		"venue": "Stevenage Arts & Leisure Centre, Lytton Way, Stevenage, SG1 1LZ",
		"mapLink": "https://maps.app.goo.gl/LVXT8SF7nTUomGLWA",
		"homeTeam": "Herts Heat",
		"awayTeam": "Ravens (WHITE)",
		"homeScore": "119",
		"awayScore": "34",
		"scoresheet": 1,
		"stats": 1,
		"squad": [
			{
				"kit": "11",
				"givenName": "Cameron",
				"familyName": "Walters",
				"available": 0
			},
			{
				"kit": "22",
				"givenName": "Damir",
				"familyName": "Davis",
				"available": 0
			},
			{
				"kit": "49",
				"givenName": "Dan",
				"familyName": "Bernard",
				"available": 0
			},
			{
				"kit": "17",
				"givenName": "Dan",
				"familyName": "Large",
				"available": 1
			},
			{
				"kit": "4",
				"givenName": "David",
				"familyName": "Shore",
				"available": 1
			},
			{
				"kit": "5",
				"givenName": "Dominic",
				"familyName": "Garcia",
				"available": 1
			},
			{
				"kit": "24",
				"givenName": "Gaetano",
				"familyName": "Lo Nigro",
				"available": 1
			},
			{
				"kit": "28",
				"givenName": "Greg",
				"familyName": "Seymour",
				"available": 0
			},
			{
				"kit": "0",
				"givenName": "Keith",
				"familyName": "Bragg",
				"available": 1
			},
			{
				"kit": "55",
				"givenName": "Lester",
				"familyName": "Confessor",
				"available": 0
			},
			{
				"kit": "33",
				"givenName": "Neil",
				"familyName": "McCutcheon",
				"available": 1
			},
			{
				"kit": "7",
				"givenName": "Otto",
				"familyName": "Opiyo",
				"available": 1
			},
			{
				"kit": "6",
				"givenName": "Richard",
				"familyName": "Herbert",
				"available": 1
			},
			{
				"kit": "14",
				"givenName": "Simon",
				"familyName": "Jackson-Turner",
				"available": 1
			}
		],
		"officials": []
	},
	{
		"datetime": "2026-03-02T20:15",
		"venue": "Onslow St Audrey's School, Old Rectory Drive, Hatfield, AL10 8AB",
		"mapLink": "https://maps.app.goo.gl/GwVjSFaKvrV3f3THA",
		"homeTeam": "Ravens (BLACK)",
		"awayTeam": "Hemel Wolves 2",
		"homeScore": "",
		"awayScore": "",
		"scoresheet": 0,
		"stats": 0,
		"squad": [
			{
				"kit": "11",
				"givenName": "Cameron",
				"familyName": "Walters",
				"available": 0
			},
			{
				"kit": "22",
				"givenName": "Damir",
				"familyName": "Davis",
				"available": 0
			},
			{
				"kit": "49",
				"givenName": "Dan",
				"familyName": "Bernard",
				"available": 0
			},
			{
				"kit": "17",
				"givenName": "Dan",
				"familyName": "Large",
				"available": 1
			},
			{
				"kit": "4",
				"givenName": "David",
				"familyName": "Shore",
				"available": 1
			},
			{
				"kit": "5",
				"givenName": "Dominic",
				"familyName": "Garcia",
				"available": 1
			},
			{
				"kit": "24",
				"givenName": "Gaetano",
				"familyName": "Lo Nigro",
				"available": 0
			},
			{
				"kit": "28",
				"givenName": "Greg",
				"familyName": "Seymour",
				"available": 0
			},
			{
				"kit": "0",
				"givenName": "Keith",
				"familyName": "Bragg",
				"available": 1
			},
			{
				"kit": "55",
				"givenName": "Lester",
				"familyName": "Confessor",
				"available": 0
			},
			{
				"kit": "33",
				"givenName": "Neil",
				"familyName": "McCutcheon",
				"available": 0
			},
			{
				"kit": "7",
				"givenName": "Otto",
				"familyName": "Opiyo",
				"available": 1
			},
			{
				"kit": "6",
				"givenName": "Richard",
				"familyName": "Herbert",
				"available": 1
			},
			{
				"kit": "14",
				"givenName": "Simon",
				"familyName": "Jackson-Turner",
				"available": 0
			}
		],
		"officials": []
	},
	{
		"datetime": "2026-02-02T20:15",
		"venue": "Onslow St Audrey's School, Old Rectory Drive, Hatfield, AL10 8AB",
		"mapLink": "https://maps.app.goo.gl/GwVjSFaKvrV3f3THA",
		"homeTeam": "Ravens (WHITE)",
		"awayTeam": "Oaklands Vets",
		"homeScore": "18",
		"awayScore": "62",
		"scoresheet": 1,
		"stats": 1,
		"squad": [
			{
				"kit": "11",
				"givenName": "Cameron",
				"familyName": "Walters",
				"available": 0
			},
			{
				"kit": "22",
				"givenName": "Damir",
				"familyName": "Davis",
				"available": 0
			},
			{
				"kit": "49",
				"givenName": "Dan",
				"familyName": "Bernard",
				"available": 1
			},
			{
				"kit": "17",
				"givenName": "Dan",
				"familyName": "Large",
				"available": 1
			},
			{
				"kit": "4",
				"givenName": "David",
				"familyName": "Shore",
				"available": 1
			},
			{
				"kit": "5",
				"givenName": "Dominic",
				"familyName": "Garcia",
				"available": 0
			},
			{
				"kit": "24",
				"givenName": "Gaetano",
				"familyName": "Lo Nigro",
				"available": 1
			},
			{
				"kit": "28",
				"givenName": "Greg",
				"familyName": "Seymour",
				"available": 0
			},
			{
				"kit": "0",
				"givenName": "Keith",
				"familyName": "Bragg",
				"available": 0
			},
			{
				"kit": "55",
				"givenName": "Lester",
				"familyName": "Confessor",
				"available": 0
			},
			{
				"kit": "33",
				"givenName": "Neil",
				"familyName": "McCutcheon",
				"available": 1
			},
			{
				"kit": "7",
				"givenName": "Otto",
				"familyName": "Opiyo",
				"available": 1
			},
			{
				"kit": "6",
				"givenName": "Richard",
				"familyName": "Herbert",
				"available": 1
			},
			{
				"kit": "14",
				"givenName": "Simon",
				"familyName": "Jackson-Turner",
				"available": 1
			}
		],
		"officials": []
	},
	{
		"datetime": "2026-02-16T20:15",
		"venue": "Onslow St Audrey's School, Old Rectory Drive, Hatfield, AL10 8AB",
		"mapLink": "https://maps.app.goo.gl/GwVjSFaKvrV3f3THA",
		"homeTeam": "Ravens (WHITE)",
		"awayTeam": "Hatfield Magic",
		"homeScore": "54",
		"awayScore": "61",
		"scoresheet": 0,
		"stats": 1,
		"squad": [
			{
				"kit": "11",
				"givenName": "Cameron",
				"familyName": "Walters",
				"available": 0
			},
			{
				"kit": "22",
				"givenName": "Damir",
				"familyName": "Davis",
				"available": 0
			},
			{
				"kit": "49",
				"givenName": "Dan",
				"familyName": "Bernard",
				"available": 1
			},
			{
				"kit": "17",
				"givenName": "Dan",
				"familyName": "Large",
				"available": 1
			},
			{
				"kit": "4",
				"givenName": "David",
				"familyName": "Shore",
				"available": 1
			},
			{
				"kit": "5",
				"givenName": "Dominic",
				"familyName": "Garcia",
				"available": 0
			},
			{
				"kit": "24",
				"givenName": "Gaetano",
				"familyName": "Lo Nigro",
				"available": 1
			},
			{
				"kit": "28",
				"givenName": "Greg",
				"familyName": "Seymour",
				"available": 0
			},
			{
				"kit": "0",
				"givenName": "Keith",
				"familyName": "Bragg",
				"available": 1
			},
			{
				"kit": "55",
				"givenName": "Lester",
				"familyName": "Confessor",
				"available": 0
			},
			{
				"kit": "33",
				"givenName": "Neil",
				"familyName": "McCutcheon",
				"available": 1
			},
			{
				"kit": "7",
				"givenName": "Otto",
				"familyName": "Opiyo",
				"available": 1
			},
			{
				"kit": "6",
				"givenName": "Richard",
				"familyName": "Herbert",
				"available": 0
			},
			{
				"kit": "14",
				"givenName": "Simon",
				"familyName": "Jackson-Turner",
				"available": 0
			}
		],
		"officials": []
	},
	{
		"datetime": "2026-02-24T20:20",
		"venue": "Oaklands College Sports Zone, Hatfield Rd, St Albans, AL4 OJA",
		"mapLink": "https://maps.app.goo.gl/Cchcr1TVd2KjAcCYA",
		"homeTeam": "Oaklands Vets",
		"awayTeam": "Ravens (WHITE)",
		"homeScore": "",
		"awayScore": "",
		"scoresheet": 0,
		"stats": 0,
		"squad": [
			{
				"kit": "11",
				"givenName": "Cameron",
				"familyName": "Walters",
				"available": 0
			},
			{
				"kit": "22",
				"givenName": "Damir",
				"familyName": "Davis",
				"available": 1
			},
			{
				"kit": "49",
				"givenName": "Dan",
				"familyName": "Bernard",
				"available": 0
			},
			{
				"kit": "17",
				"givenName": "Dan",
				"familyName": "Large",
				"available": 1
			},
			{
				"kit": "4",
				"givenName": "David",
				"familyName": "Shore",
				"available": 1
			},
			{
				"kit": "5",
				"givenName": "Dominic",
				"familyName": "Garcia",
				"available": 1
			},
			{
				"kit": "24",
				"givenName": "Gaetano",
				"familyName": "Lo Nigro",
				"available": 1
			},
			{
				"kit": "28",
				"givenName": "Greg",
				"familyName": "Seymour",
				"available": 0
			},
			{
				"kit": "0",
				"givenName": "Keith",
				"familyName": "Bragg",
				"available": 1
			},
			{
				"kit": "55",
				"givenName": "Lester",
				"familyName": "Confessor",
				"available": 0
			},
			{
				"kit": "33",
				"givenName": "Neil",
				"familyName": "McCutcheon",
				"available": 1
			},
			{
				"kit": "7",
				"givenName": "Otto",
				"familyName": "Opiyo",
				"available": 1
			},
			{
				"kit": "6",
				"givenName": "Richard",
				"familyName": "Herbert",
				"available": 0
			},
			{
				"kit": "14",
				"givenName": "Simon",
				"familyName": "Jackson-Turner",
				"available": 1
			}
		],
		"officials": []
	},
	{
		"datetime": "2026-03-09T20:15",
		"venue": "Onslow St Audrey's School, Old Rectory Drive, Hatfield, AL10 8AB",
		"mapLink": "https://maps.app.goo.gl/GwVjSFaKvrV3f3THA",
		"homeTeam": "Ravens (WHITE)",
		"awayTeam": "Enfield Mercenaries",
		"homeScore": "",
		"awayScore": "",
		"scoresheet": 0,
		"stats": 0,
		"squad": [
			{
				"kit": "11",
				"givenName": "Cameron",
				"familyName": "Walters",
				"available": 0
			},
			{
				"kit": "22",
				"givenName": "Damir",
				"familyName": "Davis",
				"available": 0
			},
			{
				"kit": "49",
				"givenName": "Dan",
				"familyName": "Bernard",
				"available": 0
			},
			{
				"kit": "17",
				"givenName": "Dan",
				"familyName": "Large",
				"available": 1
			},
			{
				"kit": "4",
				"givenName": "David",
				"familyName": "Shore",
				"available": 1
			},
			{
				"kit": "5",
				"givenName": "Dominic",
				"familyName": "Garcia",
				"available": 1
			},
			{
				"kit": "24",
				"givenName": "Gaetano",
				"familyName": "Lo Nigro",
				"available": 0
			},
			{
				"kit": "28",
				"givenName": "Greg",
				"familyName": "Seymour",
				"available": 0
			},
			{
				"kit": "0",
				"givenName": "Keith",
				"familyName": "Bragg",
				"available": 1
			},
			{
				"kit": "55",
				"givenName": "Lester",
				"familyName": "Confessor",
				"available": 0
			},
			{
				"kit": "33",
				"givenName": "Neil",
				"familyName": "McCutcheon",
				"available": 0
			},
			{
				"kit": "7",
				"givenName": "Otto",
				"familyName": "Opiyo",
				"available": 1
			},
			{
				"kit": "6",
				"givenName": "Richard",
				"familyName": "Herbert",
				"available": 1
			},
			{
				"kit": "14",
				"givenName": "Simon",
				"familyName": "Jackson-Turner",
				"available": 0
			}
		],
		"officials": []
	},
	{
		"datetime": "2026-03-26T20:15",
		"venue": "Pendelton Sports Centre, Stotfold Road, Arlesey, SG15 6XS",
		"mapLink": "https://maps.app.goo.gl/hSvjcdPYEpgeVNaJ6",
		"homeTeam": "North Herts Knights 2",
		"awayTeam": "Ravens",
		"homeScore": "",
		"awayScore": "",
		"scoresheet": 0,
		"stats": 0,
		"squad": [
			{
				"kit": "11",
				"givenName": "Cameron",
				"familyName": "Walters",
				"available": 0
			},
			{
				"kit": "22",
				"givenName": "Damir",
				"familyName": "Davis",
				"available": 0
			},
			{
				"kit": "49",
				"givenName": "Dan",
				"familyName": "Bernard",
				"available": 0
			},
			{
				"kit": "17",
				"givenName": "Dan",
				"familyName": "Large",
				"available": 0
			},
			{
				"kit": "4",
				"givenName": "David",
				"familyName": "Shore",
				"available": 0
			},
			{
				"kit": "5",
				"givenName": "Dominic",
				"familyName": "Garcia",
				"available": 0
			},
			{
				"kit": "24",
				"givenName": "Gaetano",
				"familyName": "Lo Nigro",
				"available": 0
			},
			{
				"kit": "28",
				"givenName": "Greg",
				"familyName": "Seymour",
				"available": 0
			},
			{
				"kit": "0",
				"givenName": "Keith",
				"familyName": "Bragg",
				"available": 0
			},
			{
				"kit": "55",
				"givenName": "Lester",
				"familyName": "Confessor",
				"available": 0
			},
			{
				"kit": "33",
				"givenName": "Neil",
				"familyName": "McCutcheon",
				"available": 0
			},
			{
				"kit": "7",
				"givenName": "Otto",
				"familyName": "Opiyo",
				"available": 0
			},
			{
				"kit": "6",
				"givenName": "Richard",
				"familyName": "Herbert",
				"available": 0
			},
			{
				"kit": "14",
				"givenName": "Simon",
				"familyName": "Jackson-Turner",
				"available": 0
			}
		],
		"officials": []
	},
	{
		"datetime": "2026-03-16T20:15",
		"venue": "Onslow St Audrey's School, Old Rectory Drive, Hatfield, AL10 8AB",
		"mapLink": "https://maps.app.goo.gl/GwVjSFaKvrV3f3THA",
		"homeTeam": "Ravens",
		"awayTeam": "Aylesbury Dux Rebels",
		"homeScore": "",
		"awayScore": "",
		"scoresheet": 0,
		"stats": 0,
		"squad": [
			{
				"kit": "11",
				"givenName": "Cameron",
				"familyName": "Walters",
				"available": 0
			},
			{
				"kit": "22",
				"givenName": "Damir",
				"familyName": "Davis",
				"available": 0
			},
			{
				"kit": "49",
				"givenName": "Dan",
				"familyName": "Bernard",
				"available": 0
			},
			{
				"kit": "17",
				"givenName": "Dan",
				"familyName": "Large",
				"available": 0
			},
			{
				"kit": "4",
				"givenName": "David",
				"familyName": "Shore",
				"available": 0
			},
			{
				"kit": "5",
				"givenName": "Dominic",
				"familyName": "Garcia",
				"available": 0
			},
			{
				"kit": "24",
				"givenName": "Gaetano",
				"familyName": "Lo Nigro",
				"available": 0
			},
			{
				"kit": "28",
				"givenName": "Greg",
				"familyName": "Seymour",
				"available": 0
			},
			{
				"kit": "0",
				"givenName": "Keith",
				"familyName": "Bragg",
				"available": 0
			},
			{
				"kit": "55",
				"givenName": "Lester",
				"familyName": "Confessor",
				"available": 0
			},
			{
				"kit": "33",
				"givenName": "Neil",
				"familyName": "McCutcheon",
				"available": 0
			},
			{
				"kit": "7",
				"givenName": "Otto",
				"familyName": "Opiyo",
				"available": 0
			},
			{
				"kit": "6",
				"givenName": "Richard",
				"familyName": "Herbert",
				"available": 0
			},
			{
				"kit": "14",
				"givenName": "Simon",
				"familyName": "Jackson-Turner",
				"available": 0
			}
		],
		"officials": []
	},
	{
		"datetime": "2026-04-13T20:15",
		"venue": "Birchwood Leisure Centre, Hatfield, AL10 0AN",
		"mapLink": "https://maps.app.goo.gl/u7XcxPe3zHjFbjtK9",
		"homeTeam": "Hatfield Magic",
		"awayTeam": "Ravens (WHITE)",
		"homeScore": "",
		"awayScore": "",
		"scoresheet": 0,
		"stats": 0,
		"squad": [
			{
				"kit": "11",
				"givenName": "Cameron",
				"familyName": "Walters",
				"available": 0
			},
			{
				"kit": "22",
				"givenName": "Damir",
				"familyName": "Davis",
				"available": 0
			},
			{
				"kit": "49",
				"givenName": "Dan",
				"familyName": "Bernard",
				"available": 0
			},
			{
				"kit": "17",
				"givenName": "Dan",
				"familyName": "Large",
				"available": 0
			},
			{
				"kit": "4",
				"givenName": "David",
				"familyName": "Shore",
				"available": 0
			},
			{
				"kit": "5",
				"givenName": "Dominic",
				"familyName": "Garcia",
				"available": 0
			},
			{
				"kit": "24",
				"givenName": "Gaetano",
				"familyName": "Lo Nigro",
				"available": 0
			},
			{
				"kit": "28",
				"givenName": "Greg",
				"familyName": "Seymour",
				"available": 0
			},
			{
				"kit": "0",
				"givenName": "Keith",
				"familyName": "Bragg",
				"available": 0
			},
			{
				"kit": "55",
				"givenName": "Lester",
				"familyName": "Confessor",
				"available": 0
			},
			{
				"kit": "33",
				"givenName": "Neil",
				"familyName": "McCutcheon",
				"available": 0
			},
			{
				"kit": "7",
				"givenName": "Otto",
				"familyName": "Opiyo",
				"available": 0
			},
			{
				"kit": "6",
				"givenName": "Richard",
				"familyName": "Herbert",
				"available": 0
			},
			{
				"kit": "14",
				"givenName": "Simon",
				"familyName": "Jackson-Turner",
				"available": 0
			}
		],
		"officials": []
	},
	{
		"datetime": "2026-04-21T19:45",
		"venue": "9 Kinetic Crescent, Mollison Avenue, Enfield, EN3 7XH",
		"mapLink": "https://maps.app.goo.gl/e1bWayEsgjanMU8M7",
		"homeTeam": "Enfield Mercenaries",
		"awayTeam": "Ravens (WHITE)",
		"homeScore": "",
		"awayScore": "",
		"scoresheet": 0,
		"stats": 0,
		"squad": [
			{
				"kit": "11",
				"givenName": "Cameron",
				"familyName": "Walters",
				"available": 0
			},
			{
				"kit": "22",
				"givenName": "Damir",
				"familyName": "Davis",
				"available": 0
			},
			{
				"kit": "49",
				"givenName": "Dan",
				"familyName": "Bernard",
				"available": 0
			},
			{
				"kit": "17",
				"givenName": "Dan",
				"familyName": "Large",
				"available": 0
			},
			{
				"kit": "4",
				"givenName": "David",
				"familyName": "Shore",
				"available": 0
			},
			{
				"kit": "5",
				"givenName": "Dominic",
				"familyName": "Garcia",
				"available": 0
			},
			{
				"kit": "24",
				"givenName": "Gaetano",
				"familyName": "Lo Nigro",
				"available": 0
			},
			{
				"kit": "28",
				"givenName": "Greg",
				"familyName": "Seymour",
				"available": 0
			},
			{
				"kit": "0",
				"givenName": "Keith",
				"familyName": "Bragg",
				"available": 0
			},
			{
				"kit": "55",
				"givenName": "Lester",
				"familyName": "Confessor",
				"available": 0
			},
			{
				"kit": "33",
				"givenName": "Neil",
				"familyName": "McCutcheon",
				"available": 0
			},
			{
				"kit": "7",
				"givenName": "Otto",
				"familyName": "Opiyo",
				"available": 0
			},
			{
				"kit": "6",
				"givenName": "Richard",
				"familyName": "Herbert",
				"available": 0
			},
			{
				"kit": "14",
				"givenName": "Simon",
				"familyName": "Jackson-Turner",
				"available": 0
			}
		],
		"officials": []
	}
]
